instantcoffea/__init__.py
instantcoffea/placeholder.py
instantcoffea-0.1.dist-info/METADATA
instantcoffea-0.1.dist-info/WHEEL
instantcoffea-0.1.dist-info/licenses/LICENSE
instantcoffea-0.1.dist-info/RECORD
