Metadata-Version: 2.4
Name: instantcoffea
Version: 0.1
Summary: COFFEA wrapper for a time-to-insight
Project-URL: Homepage, https://github.com/prayagyadav/instantcoffea
Project-URL: Issues, https://github.com/prayagyadav/instantcoffea/issues
Author-email: Prayag Yadav <prayag.yadav@cern.ch>
License-Expression: BSD-3-Clause
License-File: LICENSE
Classifier: Operating System :: OS Independent
Classifier: Programming Language :: Python :: 3
Requires-Python: >=3.10
